upload_form/__init__.py
upload_form/app_settings.py
upload_form/apps.py
upload_form/forms.py
upload_form/urls.py
upload_form/views.py
upload_form/locale/it/LC_MESSAGES/django.mo
upload_form/locale/it/LC_MESSAGES/django.po
upload_form/static/.DS_Store
upload_form/static/upload_form/.DS_Store
upload_form/static/upload_form/filelist.js
upload_form/static/upload_form/upload_form.css
upload_form/static/upload_form/upload_form.js
upload_form/static/upload_form/utils.js
upload_form/static/upload_form/icons/cloud-upload-svgrepo-com.svg
upload_form/static/upload_form/icons/trash-svgrepo-com.svg
upload_form/static/upload_form/icons/upload-svgrepo-com.svg
upload_form/templates/.DS_Store
upload_form/templates/upload_form/test.html
upload_form/templates/upload_form/upload_form.html
django_upload_form-0.5.0.dist-info/LICENSE
django_upload_form-0.5.0.dist-info/METADATA
django_upload_form-0.5.0.dist-info/WHEEL
django_upload_form-0.5.0.dist-info/top_level.txt
django_upload_form-0.5.0.dist-info/RECORD
