Metadata-Version: 2.1
Name: django-upload-form
Version: 0.5.0
Summary: A minimal (yet careful about UX) solution to upload multiple files in a Django project, using a Django-like Form Class
Home-page: http://github.com/morlandi/django-upload-form
Author: Mario Orlandi
Author-email: morlandi@brainstorm.it
License: MIT
Platform: UNKNOWN
Classifier: Development Status :: 5 - Production/Stable
Classifier: Operating System :: OS Independent
Classifier: Programming Language :: Python
Classifier: Framework :: Django
Classifier: Framework :: Django :: 1.11
Classifier: Framework :: Django :: 2.2
Classifier: Framework :: Django :: 3.0
Classifier: Intended Audience :: Developers
Classifier: License :: OSI Approved :: BSD License
Classifier: Natural Language :: English
Classifier: Programming Language :: Python :: 3.7
